MANIFEST.in
README
setup.cfg
setup.py
esteid/__init__.py
esteid/cli.py
esteid/main.py
esteid/mid_util.py
esteid/settings.py
esteid/sign_strategy.py
esteid/sk_ldap.py
esteid/sk_ocsp.py
esteid/ssh.py
esteid/util.py
esteid/certs/ee-certification-centre-root-ca.pem
esteid/certs/eid-sk-2007-ocsp.pem
esteid/certs/eid-sk-2007.pem
esteid/certs/eid-sk-ocsp.pem
esteid/certs/eid-sk.pem
esteid/certs/esteid-sk-2007-ocsp.pem
esteid/certs/esteid-sk-2007.pem
esteid/certs/esteid-sk-2011.pem
esteid/certs/esteid-sk-ocsp.pem
esteid/certs/esteid-sk.pem
esteid/certs/juur.pem
esteid/certs/klass3-sk.pem
esteid/certs/pkcs12-split.sh
esteid/certs/sk-ocsp-responder-certificates.pem
python_esteid.egg-info/PKG-INFO
python_esteid.egg-info/SOURCES.txt
python_esteid.egg-info/dependency_links.txt
python_esteid.egg-info/entry_points.txt
python_esteid.egg-info/requires.txt
python_esteid.egg-info/top_level.txt
python_esteid.egg-info/zip-safe