Metadata-Version: 1.1
Name: python-esteid
Version: 0.1.8
Summary: Utilities for Estonian eID and mID infrastructure
Home-page: https://github.com/martinpaljak/python-esteid
Author: Martin Paljak
Author-email: martin@martinpaljak.net
License: MIT
Platform: UNKNOWN
Classifier: Topic :: Utilities
Classifier: Topic :: Security :: Cryptography
Classifier: License :: OSI Approved :: MIT License
Classifier: Programming Language :: Python :: 2.5
Classifier: Programming Language :: Python :: 2.6
Classifier: Programming Language :: Python :: 2.7
Classifier: Programming Language :: Python :: Implementation :: CPython
